asciibars.py
asciibars-0.0.2.dist-info/LICENSE
asciibars-0.0.2.dist-info/METADATA
asciibars-0.0.2.dist-info/WHEEL
asciibars-0.0.2.dist-info/top_level.txt
asciibars-0.0.2.dist-info/RECORD
